.gitignore
.travis.yml
CHANGES.rst
Cargo.lock
Cargo.toml
LICENSE.txt
Makefile
README.rst
requirements-ci.txt
requirements-dev.txt
setup.py
benches/parse.rs
benchmark/echoclient.py
benchmark/echoserver.py
benchmark/rlserver.py
src/addrinfo.rs
src/callbacks.rs
src/client.rs
src/event_loop.rs
src/fd.rs
src/fut.rs
src/handle.rs
src/lib.rs
src/pybytes.rs
src/pyfuture.rs
src/pytask.rs
src/pyunsafe.rs
src/server.rs
src/signals.rs
src/socket.rs
src/transport.rs
src/utils.rs
src/http/codec.rs
src/http/decoder.rs
src/http/headers.rs
src/http/message.rs
src/http/mod.rs
src/http/pyreq.rs
src/http/pytransport.rs
src/http/status.rs
src/http/transport.rs
tests/_testbase.py
tests/conftest.py
tests/test_base.py
tests/test_dns.py
tests/test_executors.py
tests/test_futures.py
tests/test_http_decoder.rs
tests/test_pipes.py
tests/test_process.py
tests/test_pybytes.rs
tests/test_signals.py
tests/test_sockets.py
tests/test_ssl.py
tests/test_tasks.py
tests/test_tcp.py
tests/test_unix.py
tests/certs/ssl_cert.pem
tests/certs/ssl_key.pem
tokio/__init__.py
tokio/helpers.py
tokio/pytest_plugin.py
tokio/test_utils.py
tokio.egg-info/PKG-INFO
tokio.egg-info/SOURCES.txt
tokio.egg-info/dependency_links.txt
tokio.egg-info/not-zip-safe
tokio.egg-info/top_level.txt